src/__init__.py
src/__main__.py
src/my_scrapetube.py
src/validate_id.py
src/youtube_dl.py
src/youtube_to_anchorFM.py
test/__init__.py
test/test_my_scrapetube.py
test/test_validate_id.py
test/test_youtube_dl.py
tube_cast-0.1.0.dist-info/LICENSE
tube_cast-0.1.0.dist-info/METADATA
tube_cast-0.1.0.dist-info/WHEEL
tube_cast-0.1.0.dist-info/entry_points.txt
tube_cast-0.1.0.dist-info/top_level.txt
tube_cast-0.1.0.dist-info/RECORD
