Metadata-Version: 2.1
Name: tube-cast
Version: 0.1.0
Summary: A command-line tool that converts YouTube videos into Anchor FM podcasts.
Home-page: https://github.com/abe-101/tube-cast
Download-URL: https://github.com/abe-101/tube-cast/releases/download/v0.1.0/tube-cast-0.1.0.tar.gz
Author: Abe Hanoka
Author-email: abe@habet.dev
License: MIT
Classifier: Programming Language :: Python :: 3
Classifier: Programming Language :: Python :: 3.7
Requires-Python: >=3.7
License-File: LICENSE
Requires-Dist: click
Requires-Dist: scrapetube
Requires-Dist: yt-dlp
Requires-Dist: pyppeteer
